hypercrawl/__init__.py
hypercrawl/domain_scraper.py
hypercrawler-0.1.1.dist-info/LICENSE
hypercrawler-0.1.1.dist-info/METADATA
hypercrawler-0.1.1.dist-info/WHEEL
hypercrawler-0.1.1.dist-info/top_level.txt
hypercrawler-0.1.1.dist-info/RECORD
